mq_service/__init__.py
mq_service/service.py
onlive_mq/__init__.py
onlive_mq/service.py
onlive_mq-0.2.0.dist-info/LICENSE
onlive_mq-0.2.0.dist-info/METADATA
onlive_mq-0.2.0.dist-info/WHEEL
onlive_mq-0.2.0.dist-info/top_level.txt
onlive_mq-0.2.0.dist-info/RECORD
